architect/__init__.py
architect/builders.py
architect/database_reflection.py
architect/feature_dictionary_creator.py
architect/feature_generators.py
architect/feature_group_creator.py
architect/feature_group_mixer.py
architect/features.py
architect/label_generators.py
architect/planner.py
architect/state_table_generators.py
architect/utils.py
architect/validations.py
matrix_architect-1.0.1.dist-info/DESCRIPTION.rst
matrix_architect-1.0.1.dist-info/METADATA
matrix_architect-1.0.1.dist-info/RECORD
matrix_architect-1.0.1.dist-info/WHEEL
matrix_architect-1.0.1.dist-info/metadata.json
matrix_architect-1.0.1.dist-info/top_level.txt
