Metadata-Version: 2.0
Name: matrix-architect
Version: 1.0.1
Summary: Plan, design, and build train and test matrices
Home-page: https://github.com/dssg/architect
Author: Center for Data Science and Public Policy
Author-email: datascifellows@gmail.com
License: BY DOWNLOADING architect PROGRAM YOU AGREE TO THE FOLLOWING TERMS OF USE:
Requires-Dist: collate (==0.3.0)
Requires-Dist: metta-data (>=1.0)
Requires-Dist: psycopg2
Requires-Dist: results-schema (>=2.0)
Requires-Dist: sqlalchemy
